{"mc":{"game_720_effect_logo":{"frameRate":24,"labels":[{"name":"game_720_effect_logo","frame":1,"end":22}],"events":[],"frames":[{"res":"game_720_effect_logo_0","x":6,"y":5},{"res":"game_720_effect_logo_1","x":5,"y":5},{"res":"game_720_effect_logo_2","x":5,"y":5},{"res":"game_720_effect_logo_3","x":6,"y":5},{"res":"game_720_effect_logo_4","x":5,"y":5},{"res":"game_720_effect_logo_5","x":6,"y":5},{"res":"game_720_effect_logo_6","x":5,"y":5},{"res":"game_720_effect_logo_7","x":6,"y":5},{"res":"game_720_effect_logo_8","x":6,"y":5},{"res":"game_720_effect_logo_9","x":5,"y":2},{"res":"game_720_effect_logo_10","x":3,"y":0},{"res":"game_720_effect_logo_11","x":4,"y":0},{"res":"game_720_effect_logo_12","x":6,"y":0},{"res":"game_720_effect_logo_13","x":2,"y":0},{"res":"game_720_effect_logo_14","x":0,"y":0},{"res":"game_720_effect_logo_15","x":0,"y":0},{"res":"game_720_effect_logo_16","x":0,"y":0},{"res":"game_720_effect_logo_17","x":0,"y":0},{"res":"game_720_effect_logo_18","x":0,"y":0},{"res":"game_720_effect_logo_19","x":0,"y":0},{"res":"game_720_effect_logo_20","x":5,"y":5},{"res":"game_720_effect_logo_21","x":5,"y":5}]}},"res":{"game_720_effect_logo_5":{"x":261,"y":472,"w":85,"h":151},"game_720_effect_logo_21":{"x":357,"y":467,"w":87,"h":151},"game_720_effect_logo_12":{"x":270,"y":314,"w":85,"h":156},"game_720_effect_logo_11":{"x":181,"y":158,"w":87,"h":156},"game_720_effect_logo_15":{"x":372,"y":0,"w":91,"h":155},"game_720_effect_logo_0":{"x":87,"y":469,"w":85,"h":151},"game_720_effect_logo_10":{"x":91,"y":158,"w":88,"h":156},"game_720_effect_logo_8":{"x":348,"y":620,"w":85,"h":151},"game_720_effect_logo_4":{"x":89,"y":316,"w":87,"h":151},"game_720_effect_logo_3":{"x":0,"y":469,"w":85,"h":151},"game_720_effect_logo_7":{"x":174,"y":469,"w":85,"h":151},"game_720_effect_logo_9":{"x":270,"y":158,"w":87,"h":154},"game_720_effect_logo_2":{"x":357,"y":314,"w":87,"h":151},"game_720_effect_logo_14":{"x":93,"y":0,"w":91,"h":156},"game_720_effect_logo_1":{"x":0,"y":316,"w":87,"h":151},"game_720_effect_logo_6":{"x":178,"y":316,"w":87,"h":151},"game_720_effect_logo_18":{"x":186,"y":0,"w":91,"h":156},"game_720_effect_logo_19":{"x":279,"y":0,"w":91,"h":156},"game_720_effect_logo_20":{"x":357,"y":467,"w":87,"h":151},"game_720_effect_logo_17":{"x":372,"y":157,"w":91,"h":155},"game_720_effect_logo_16":{"x":0,"y":0,"w":91,"h":156},"game_720_effect_logo_13":{"x":0,"y":158,"w":89,"h":156}}}