{"mc":{
	"game_730_effect":{
		"frameRate":24,
		"labels":[
			{"name":"game_730_effect","frame":1,"end":24}
			
			],
		"events":[
			
			],
		"frames":[
			
			{
			"res":"game_730_effect_0",
			"x":0,
			"y":0
			},
			{
			"res":"game_730_effect_1",
			"x":0,
			"y":0
			},
			{
			"res":"game_730_effect_2",
			"x":0,
			"y":0
			},
			{
			"res":"game_730_effect_3",
			"x":0,
			"y":0
			},
			{
			"res":"game_730_effect_4",
			"x":0,
			"y":0
			},
			{
			"res":"game_730_effect_5",
			"x":0,
			"y":0
			},
			{
			"res":"game_730_effect_6",
			"x":0,
			"y":0
			},
			{
			"res":"game_730_effect_7",
			"x":0,
			"y":0
			},
			{
			"res":"game_730_effect_8",
			"x":0,
			"y":0
			},
			{
			"res":"game_730_effect_9",
			"x":0,
			"y":0
			},
			{
			"res":"game_730_effect_10",
			"x":0,
			"y":0
			},
			{
			"res":"game_730_effect_11",
			"x":0,
			"y":0
			},
			{
			"res":"game_730_effect_12",
			"x":0,
			"y":0
			},
			{
			"res":"game_730_effect_13",
			"x":0,
			"y":0
			},
			{
			"res":"game_730_effect_14",
			"x":0,
			"y":0
			},
			{
			"res":"game_730_effect_15",
			"x":0,
			"y":0
			},
			{
			"res":"game_730_effect_16",
			"x":0,
			"y":0
			},
			{
			"res":"game_730_effect_17",
			"x":0,
			"y":0
			},
			{
			"res":"game_730_effect_18",
			"x":0,
			"y":0
			},
			{
			"res":"game_730_effect_19",
			"x":0,
			"y":0
			},
			{
			"res":"game_730_effect_20",
			"x":0,
			"y":0
			},
			{
			"res":"game_730_effect_21",
			"x":0,
			"y":0
			},
			{
			"res":"game_730_effect_22",
			"x":0,
			"y":0
			},
			{
			"res":"game_730_effect_23",
			"x":0,
			"y":0
			}
			]
}},
	"res":{
		"game_730_effect_17":{"x":0,"y":564,"w":250,"h":280},
		"game_730_effect_4":{"x":504,"y":282,"w":250,"h":280},
		"game_730_effect_13":{"x":504,"y":564,"w":250,"h":280},
		"game_730_effect_20":{"x":252,"y":0,"w":250,"h":280},
		"game_730_effect_9":{"x":756,"y":564,"w":250,"h":280},
		"game_730_effect_23":{"x":504,"y":0,"w":250,"h":280},
		"game_730_effect_19":{"x":0,"y":846,"w":250,"h":280},
		"game_730_effect_8":{"x":504,"y":846,"w":250,"h":280},
		"game_730_effect_15":{"x":252,"y":1128,"w":250,"h":280},
		"game_730_effect_16":{"x":252,"y":282,"w":250,"h":280},
		"game_730_effect_22":{"x":756,"y":1128,"w":250,"h":280},
		"game_730_effect_1":{"x":0,"y":1128,"w":250,"h":280},
		"game_730_effect_3":{"x":252,"y":846,"w":250,"h":280},
		"game_730_effect_21":{"x":756,"y":846,"w":250,"h":280},
		"game_730_effect_2":{"x":756,"y":1410,"w":250,"h":280},
		"game_730_effect_0":{"x":0,"y":0,"w":250,"h":280},
		"game_730_effect_6":{"x":0,"y":1410,"w":250,"h":280},
		"game_730_effect_14":{"x":756,"y":282,"w":250,"h":280},
		"game_730_effect_18":{"x":504,"y":1128,"w":250,"h":280},
		"game_730_effect_7":{"x":252,"y":1410,"w":250,"h":280},
		"game_730_effect_12":{"x":504,"y":1410,"w":250,"h":280},
		"game_730_effect_5":{"x":252,"y":564,"w":250,"h":280},
		"game_730_effect_10":{"x":756,"y":0,"w":250,"h":280},
		"game_730_effect_11":{"x":0,"y":282,"w":250,"h":280}
	}}